uklatn.py
tests/__init__.py
tests/uklatn_tests.py
uklatn-1.20.0.dist-info/METADATA
uklatn-1.20.0.dist-info/WHEEL
uklatn-1.20.0.dist-info/top_level.txt
uklatn-1.20.0.dist-info/RECORD
