Metadata-Version: 2.1
Name: uklatn
Version: 1.20.0
Summary: Ukrainian Cyrillic transliteration to Latin script
Author: Pavlo Ivashkov
License: MIT License Copyright (c) 2024 Pavel Ivashkov https://github.com/paiv
Project-URL: homepage, https://github.com/paiv/uklatn
Project-URL: source, https://github.com/paiv/uklatn
Keywords: ukraine,translit,romanization
Classifier: License :: OSI Approved :: MIT License
Requires-Python: >=3.10
